{
    "images": [
        {
            "startdate": "20251229",
            "fullstartdate": "202512292300",
            "enddate": "20251230",
            "url": "/th?id=OHR.JapanSwans_DE-DE3934541892_1920x1080.jpg&rf=LaDigue_1920x1080.jpg&pid=hp",
            "urlbase": "/th?id=OHR.JapanSwans_DE-DE3934541892",
            "copyright": "Singschwäne, Kotoku-Teich, Japan (© Martin Bailey/Shutterstock)",
            "copyrightlink": "https://www.bing.com/search?q=Singschwan&form=hpcapt&filters=HpDate%3a%2220251229_2300%22",
            "title": "Ein Tanz mit dem Wind",
            "quiz": "/search?q=Bing+homepage+quiz&filters=WQOskey:%22HPQuiz_20251229_JapanSwans%22&FORM=HPQUIZ",
            "wp": true,
            "hsh": "f0e31d1780bd38f1163dc840e3491589",
            "drk": 1,
            "top": 1,
            "bot": 1,
            "hs": []
        },
        {
            "startdate": "20251228",
            "fullstartdate": "202512282300",
            "enddate": "20251229",
            "url": "/th?id=OHR.SkijumpingEisenbichler_DE-DE4421399020_1920x1080.jpg&rf=LaDigue_1920x1080.jpg&pid=hp",
            "urlbase": "/th?id=OHR.SkijumpingEisenbichler_DE-DE4421399020",
            "copyright": "Markus Eisenbichler (GER) beim ersten Sprung am zweiten Tag der Vierschanzentournee, 30. Dezember 2016, Oberstdorf, Bayern (© Adam Pretty/Getty Images)",
            "copyrightlink": "https://www.bing.com/search?q=Vierschanzentournee&form=hpcapt&filters=HpDate%3a%2220251228_2300%22",
            "title": "Lichter, Weite, Adrenalin",
            "quiz": "/search?q=Bing+homepage+quiz&filters=WQOskey:%22HPQuiz_20251228_SkijumpingEisenbichler%22&FORM=HPQUIZ",
            "wp": false,
            "hsh": "7ff9d3df701b3a8d8d8d5e0eaa7daeaa",
            "drk": 1,
            "top": 1,
            "bot": 1,
            "hs": []
        },
        {
            "startdate": "20251227",
            "fullstartdate": "202512272300",
            "enddate": "20251228",
            "url": "/th?id=OHR.RuffedLemur_DE-DE7591770209_1920x1080.jpg&rf=LaDigue_1920x1080.jpg&pid=hp",
            "urlbase": "/th?id=OHR.RuffedLemur_DE-DE7591770209",
            "copyright": "Schwarzweißer Vari auf Madagaskar (© Cyrielle Beaubois/Getty Images)",
            "copyrightlink": "https://www.bing.com/search?q=Lemuren&form=hpcapt&filters=HpDate%3a%2220251227_2300%22",
            "title": "Wächter des Waldes",
            "quiz": "/search?q=Bing+homepage+quiz&filters=WQOskey:%22HPQuiz_20251227_RuffedLemur%22&FORM=HPQUIZ",
            "wp": true,
            "hsh": "f1053ab7648d0db7ed012fc93e73f21c",
            "drk": 1,
            "top": 1,
            "bot": 1,
            "hs": []
        },
        {
            "startdate": "20251226",
            "fullstartdate": "202512262300",
            "enddate": "20251227",
            "url": "/th?id=OHR.SuperiorIceMN_DE-DE3366559163_1920x1080.jpg&rf=LaDigue_1920x1080.jpg&pid=hp",
            "urlbase": "/th?id=OHR.SuperiorIceMN_DE-DE3366559163",
            "copyright": "Platteneis entlang des Oberen Sees, Grand Marais, Minnesota, USA (© wanderluster/Getty Images)",
            "copyrightlink": "https://www.bing.com/search?q=Oberer+See+Minnesota&form=hpcapt&filters=HpDate%3a%2220251226_2300%22",
            "title": "Scherben des Winters",
            "quiz": "/search?q=Bing+homepage+quiz&filters=WQOskey:%22HPQuiz_20251226_SuperiorIceMN%22&FORM=HPQUIZ",
            "wp": true,
            "hsh": "f485389a8f838508676f0a933df1ced6",
            "drk": 1,
            "top": 1,
            "bot": 1,
            "hs": []
        },
        {
            "startdate": "20251225",
            "fullstartdate": "202512252300",
            "enddate": "20251226",
            "url": "/th?id=OHR.WiltshireDawn_DE-DE2989262973_1920x1080.jpg&rf=LaDigue_1920x1080.jpg&pid=hp",
            "urlbase": "/th?id=OHR.WiltshireDawn_DE-DE2989262973",
            "copyright": "Kathedrale von Salisbury, Wiltshire, England (© Julian Elliott Photography/Getty Images)",
            "copyrightlink": "https://www.bing.com/search?q=Zweiter+Weihnachtsfeiertag&form=hpcapt&filters=HpDate%3a%2220251225_2300%22",
            "title": "Tradition trifft Entspannung",
            "quiz": "/search?q=Bing+homepage+quiz&filters=WQOskey:%22HPQuiz_20251225_WiltshireDawn%22&FORM=HPQUIZ",
            "wp": true,
            "hsh": "dfdd5d4bbd5a50130f1383bd6aadedb3",
            "drk": 1,
            "top": 1,
            "bot": 1,
            "hs": []
        },
        {
            "startdate": "20251224",
            "fullstartdate": "202512242300",
            "enddate": "20251225",
            "url": "/th?id=OHR.SantaGlobe_DE-DE3146908571_1920x1080.jpg&rf=LaDigue_1920x1080.jpg&pid=hp",
            "urlbase": "/th?id=OHR.SantaGlobe_DE-DE3146908571",
            "copyright": "Schneekugeln auf einem Weihnachtsmarkt in Heidelberg, Baden-Württemberg (© George Pachantouris/Getty Images)",
            "copyrightlink": "https://www.bing.com/search?q=Weihnachten&form=hpcapt&filters=HpDate%3a%2220251224_2300%22",
            "title": "Kleine Welten, großer Zauber",
            "quiz": "/search?q=Bing+homepage+quiz&filters=WQOskey:%22HPQuiz_20251224_SantaGlobe%22&FORM=HPQUIZ",
            "wp": true,
            "hsh": "d47b60cd5d8a20755921a57439cd175c",
            "drk": 1,
            "top": 1,
            "bot": 1,
            "hs": []
        },
        {
            "startdate": "20251223",
            "fullstartdate": "202512232300",
            "enddate": "20251224",
            "url": "/th?id=OHR.ElmauSnow_DE-DE2680814765_1920x1080.jpg&rf=LaDigue_1920x1080.jpg&pid=hp",
            "urlbase": "/th?id=OHR.ElmauSnow_DE-DE2680814765",
            "copyright": "Kapelle und Weihnachtsbaum in winterlicher Landschaft, Elmau, Bayern (© Michael Thaler/Shutterstock)",
            "copyrightlink": "https://www.bing.com/search?q=Heiligabend&form=hpcapt&filters=HpDate%3a%2220251223_2300%22",
            "title": "Stille Nacht, heilige Nacht!",
            "quiz": "/search?q=Bing+homepage+quiz&filters=WQOskey:%22HPQuiz_20251223_ElmauSnow%22&FORM=HPQUIZ",
            "wp": true,
            "hsh": "c0a8e45c064a9a305a224822dab63464",
            "drk": 1,
            "top": 1,
            "bot": 1,
            "hs": []
        },
        {
            "startdate": "20251222",
            "fullstartdate": "202512222300",
            "enddate": "20251223",
            "url": "/th?id=OHR.ReindeerFinland_DE-DE2067489685_1920x1080.jpg&rf=LaDigue_1920x1080.jpg&pid=hp",
            "urlbase": "/th?id=OHR.ReindeerFinland_DE-DE2067489685",
            "copyright": "Rentiere während des Schneefalls im Winter, Lappland, Finnland (© Roberto Moiola/Getty Images)",
            "copyrightlink": "https://www.bing.com/search?q=Rentier&form=hpcapt&filters=HpDate%3a%2220251222_2300%22",
            "title": "Hüter des Schnees",
            "quiz": "/search?q=Bing+homepage+quiz&filters=WQOskey:%22HPQuiz_20251222_ReindeerFinland%22&FORM=HPQUIZ",
            "wp": true,
            "hsh": "2dbfc354d4bd4bbc0a1f14effafc1399",
            "drk": 1,
            "top": 1,
            "bot": 1,
            "hs": []
        }
    ],
    "tooltips": {
        "loading": "Wird geladen...",
        "previous": "Vorheriges Bild",
        "next": "Nächstes Bild",
        "walle": "Dieses Bild steht nicht zum Download als Hintergrundbild zur Verfügung.",
        "walls": "Dieses Bild herunterladen. Dieses Bild darf nur als Hintergrundbild verwendet werden."
    }
}