{
    "images": [
        {
            "startdate": "20220923",
            "fullstartdate": "202209231500",
            "enddate": "20220924",
            "url": "/th?id=OHR.DarkSkyAcadia_JA-JP2177649071_1920x1080.jpg&rf=LaDigue_1920x1080.jpg&pid=hp",
            "urlbase": "/th?id=OHR.DarkSkyAcadia_JA-JP2177649071",
            "copyright": "アーカディア国立公園の夜空に架かる天の川, 米国 メイン州 (© Harry Collins/Getty Images)",
            "copyrightlink": "https://www.bing.com/search?q=%E3%82%A2%E3%83%BC%E3%82%AB%E3%83%87%E3%82%A3%E3%82%A2%E5%9B%BD%E7%AB%8B%E5%85%AC%E5%9C%92&form=hpcapt&filters=HpDate%3a%2220220923_1500%22",
            "title": "アーカディア国立公園",
            "quiz": "/search?q=Bing+homepage+quiz&filters=WQOskey:%22HPQuiz_20220923_DarkSkyAcadia%22&FORM=HPQUIZ",
            "wp": true,
            "hsh": "8ca85c657b7e0aed2d9c5cb8da76080e",
            "drk": 1,
            "top": 1,
            "bot": 1,
            "hs": []
        },
        {
            "startdate": "20220922",
            "fullstartdate": "202209221500",
            "enddate": "20220923",
            "url": "/th?id=OHR.LastDollarRoad_JA-JP2023000360_1920x1080.jpg&rf=LaDigue_1920x1080.jpg&pid=hp",
            "urlbase": "/th?id=OHR.LastDollarRoad_JA-JP2023000360",
            "copyright": "アスペンの紅葉 ラストダラーロード, 米国 コロラド州 (© Grant Ordelheide/Tandem Stills + Motion)",
            "copyrightlink": "https://www.bing.com/search?q=%E3%83%A9%E3%82%B9%E3%83%88%E3%83%80%E3%83%A9%E3%83%BC%E3%83%AD%E3%83%BC%E3%83%89&form=hpcapt&filters=HpDate%3a%2220220922_1500%22",
            "title": "今日は秋分の日",
            "quiz": "/search?q=Bing+homepage+quiz&filters=WQOskey:%22HPQuiz_20220922_LastDollarRoad%22&FORM=HPQUIZ",
            "wp": true,
            "hsh": "95d4512f0b4443cea551849d6fa30864",
            "drk": 1,
            "top": 1,
            "bot": 1,
            "hs": []
        },
        {
            "startdate": "20220921",
            "fullstartdate": "202209211500",
            "enddate": "20220922",
            "url": "/th?id=OHR.RhinocerosUnicornis_JA-JP5127781121_1920x1080.jpg&rf=LaDigue_1920x1080.jpg&pid=hp",
            "urlbase": "/th?id=OHR.RhinocerosUnicornis_JA-JP5127781121",
            "copyright": "インドサイ, インド アッサム州 (© Robert Harding World Imagery/Shutterstock)",
            "copyrightlink": "https://www.bing.com/search?q=%E3%82%A4%E3%83%B3%E3%83%89%E3%82%B5%E3%82%A4&form=hpcapt&filters=HpDate%3a%2220220921_1500%22",
            "title": "今日は世界サイの日",
            "quiz": "/search?q=Bing+homepage+quiz&filters=WQOskey:%22HPQuiz_20220921_RhinocerosUnicornis%22&FORM=HPQUIZ",
            "wp": true,
            "hsh": "14b29c955f7c15750c95d28c36a983ea",
            "drk": 1,
            "top": 1,
            "bot": 1,
            "hs": []
        },
        {
            "startdate": "20220920",
            "fullstartdate": "202209201500",
            "enddate": "20220921",
            "url": "/th?id=OHR.PWPeaceDoves_JA-JP4761211856_1920x1080.jpg&rf=LaDigue_1920x1080.jpg&pid=hp",
            "urlbase": "/th?id=OHR.PWPeaceDoves_JA-JP4761211856",
            "copyright": "”Peace Doves” ピーター・ウォーカー,  イギリス リヴァプール (© PAUL ELLIS/AFP via Getty Images)",
            "copyrightlink": "https://www.bing.com/search?q=%E3%83%AA%E3%83%B4%E3%82%A1%E3%83%97%E3%83%BC%E3%83%AB%E5%A4%A7%E8%81%96%E5%A0%82&form=hpcapt&filters=HpDate%3a%2220220920_1500%22",
            "title": "今日は国際平和デー",
            "quiz": "/search?q=Bing+homepage+quiz&filters=WQOskey:%22HPQuiz_20220920_PWPeaceDoves%22&FORM=HPQUIZ",
            "wp": false,
            "hsh": "7cd54bba27f1b7635d249f60a4d86260",
            "drk": 1,
            "top": 1,
            "bot": 1,
            "hs": []
        },
        {
            "startdate": "20220919",
            "fullstartdate": "202209191500",
            "enddate": "20220920",
            "url": "/th?id=OHR.SitkaOtters_JA-JP3956360423_1920x1080.jpg&rf=LaDigue_1920x1080.jpg&pid=hp",
            "urlbase": "/th?id=OHR.SitkaOtters_JA-JP3956360423",
            "copyright": "ラッコの群れ, 米国 アラスカ州 (© Robert Harding/Offset/Shutterstock)",
            "copyrightlink": "https://www.bing.com/search?q=%E3%83%A9%E3%83%83%E3%82%B3%E3%81%AE%E7%BE%A4%E3%82%8C&form=hpcapt&filters=HpDate%3a%2220220919_1500%22",
            "title": "今週はラッコ啓蒙週間",
            "quiz": "/search?q=Bing+homepage+quiz&filters=WQOskey:%22HPQuiz_20220919_SitkaOtters%22&FORM=HPQUIZ",
            "wp": true,
            "hsh": "9bf151fa36c92de9929cb91ff2e5aa36",
            "drk": 1,
            "top": 1,
            "bot": 1,
            "hs": []
        },
        {
            "startdate": "20220918",
            "fullstartdate": "202209181500",
            "enddate": "20220919",
            "url": "/th?id=OHR.OldOwl2022_JA-JP6310024287_1920x1080.jpg&rf=LaDigue_1920x1080.jpg&pid=hp",
            "urlbase": "/th?id=OHR.OldOwl2022_JA-JP6310024287",
            "copyright": "樹木に溶け込むフクロウ (© Shin Yoshino/Minden)",
            "copyrightlink": "https://www.bing.com/search?q=%E3%82%AA%E3%82%AA%E3%82%B3%E3%83%8E%E3%83%8F%E3%82%BA%E3%82%AF&form=hpcapt&filters=HpDate%3a%2220220918_1500%22",
            "title": "今日は敬老の日",
            "quiz": "/search?q=Bing+homepage+quiz&filters=WQOskey:%22HPQuiz_20220918_OldOwl2022%22&FORM=HPQUIZ",
            "wp": true,
            "hsh": "79ff229106cfd502a565fd44a3e5ccc1",
            "drk": 1,
            "top": 1,
            "bot": 1,
            "hs": []
        },
        {
            "startdate": "20220917",
            "fullstartdate": "202209171500",
            "enddate": "20220918",
            "url": "/th?id=OHR.ArashiyamaBamboo_JA-JP3173053038_1920x1080.jpg&rf=LaDigue_1920x1080.jpg&pid=hp",
            "urlbase": "/th?id=OHR.ArashiyamaBamboo_JA-JP3173053038",
            "copyright": "竹林の小径, 京都 嵐山 (© Razvan Ciuca/Getty Images)",
            "copyrightlink": "https://www.bing.com/search?q=%E7%AB%B9%E6%9E%97%E3%81%AE%E5%B0%8F%E5%BE%84&form=hpcapt&filters=HpDate%3a%2220220917_1500%22",
            "title": "今日は世界竹の日",
            "quiz": "/search?q=Bing+homepage+quiz&filters=WQOskey:%22HPQuiz_20220917_ArashiyamaBamboo%22&FORM=HPQUIZ",
            "wp": true,
            "hsh": "50d565e6787788d816aa033ea67aff92",
            "drk": 1,
            "top": 1,
            "bot": 1,
            "hs": []
        },
        {
            "startdate": "20220916",
            "fullstartdate": "202209161500",
            "enddate": "20220917",
            "url": "/th?id=OHR.Wellenflug_JA-JP2926731181_1920x1080.jpg&rf=LaDigue_1920x1080.jpg&pid=hp",
            "urlbase": "/th?id=OHR.Wellenflug_JA-JP2926731181",
            "copyright": "オクトーバーフェスト, ドイツ ミュンヘン (© Karl-Josef Hildenbrand/Getty Images)",
            "copyrightlink": "https://www.bing.com/search?q=%E3%82%AA%E3%82%AF%E3%83%88%E3%83%BC%E3%83%90%E3%83%BC%E3%83%95%E3%82%A7%E3%82%B9%E3%83%88&form=hpcapt&filters=HpDate%3a%2220220916_1500%22",
            "title": "ドイツのオクトーバーフェスト",
            "quiz": "/search?q=Bing+homepage+quiz&filters=WQOskey:%22HPQuiz_20220916_Wellenflug%22&FORM=HPQUIZ",
            "wp": false,
            "hsh": "e25177ce9a2f9c7949c3eb89289c896a",
            "drk": 1,
            "top": 1,
            "bot": 1,
            "hs": []
        }
    ],
    "tooltips": {
        "loading": "読み込み中...",
        "previous": "前の画像へ",
        "next": "次の画像へ",
        "walle": "この画像を壁紙としてダウンロードすることはできません。",
        "walls": "この画像をダウンロードできます。画像の用途は壁紙に限定されています。"
    }
}