{
    "images": [
        {
            "startdate": "20231020",
            "fullstartdate": "202310202300",
            "enddate": "20231021",
            "url": "/th?id=OHR.PersepolisRelief_EN-GB3727800010_1920x1080.jpg&rf=LaDigue_1920x1080.jpg&pid=hp",
            "urlbase": "/th?id=OHR.PersepolisRelief_EN-GB3727800010",
            "copyright": "Reliefs in the ancient Persian city of Persepolis, Iran (© Ozbalci/Getty Images)",
            "copyrightlink": "https://www.bing.com/search?q=City+of+Persepolis&form=hpcapt&filters=HpDate%3a%2220231020_2300%22",
            "title": "Wow, what a relief!",
            "quiz": "/search?q=Bing+homepage+quiz&filters=WQOskey:%22HPQuiz_20231020_PersepolisRelief%22&FORM=HPQUIZ",
            "wp": true,
            "hsh": "7d1f285ddb3dcf8c3967db424357cf72",
            "drk": 1,
            "top": 1,
            "bot": 1,
            "hs": []
        },
        {
            "startdate": "20231019",
            "fullstartdate": "202310192300",
            "enddate": "20231020",
            "url": "/th?id=OHR.PygmySloth_EN-GB3183827420_1920x1080.jpg&rf=LaDigue_1920x1080.jpg&pid=hp",
            "urlbase": "/th?id=OHR.PygmySloth_EN-GB3183827420",
            "copyright": "Pygmy three-toed sloth baby, Isla Escudo de Veraguas, Panama (© Suzi Eszterhas/Minden Pictures)",
            "copyrightlink": "https://www.bing.com/search?q=sloth+animal&form=hpcapt&filters=HpDate%3a%2220231019_2300%22",
            "title": "Do you wanna hang?",
            "quiz": "/search?q=Bing+homepage+quiz&filters=WQOskey:%22HPQuiz_20231019_PygmySloth%22&FORM=HPQUIZ",
            "wp": true,
            "hsh": "48b053a576294dcb5df90d24bcb77591",
            "drk": 1,
            "top": 1,
            "bot": 1,
            "hs": []
        },
        {
            "startdate": "20231018",
            "fullstartdate": "202310182300",
            "enddate": "20231019",
            "url": "/th?id=OHR.WaterLilyVietnam_EN-GB4801163561_1920x1080.jpg&rf=LaDigue_1920x1080.jpg&pid=hp",
            "urlbase": "/th?id=OHR.WaterLilyVietnam_EN-GB4801163561",
            "copyright": "Water lily harvest, Mekong River Delta, Long An, Vietnam (© Khanh Phan/Solent News/Shutterstock)",
            "copyrightlink": "https://www.bing.com/search?q=Mekong+River+Delta&form=hpcapt&filters=HpDate%3a%2220231018_2300%22",
            "title": "Teamwork makes the dream work",
            "quiz": "/search?q=Bing+homepage+quiz&filters=WQOskey:%22HPQuiz_20231018_WaterLilyVietnam%22&FORM=HPQUIZ",
            "wp": false,
            "hsh": "1df534e874ed83982bfafac3dc79b399",
            "drk": 1,
            "top": 1,
            "bot": 1,
            "hs": []
        },
        {
            "startdate": "20231017",
            "fullstartdate": "202310172300",
            "enddate": "20231018",
            "url": "/th?id=OHR.CanaryWharfStation_EN-GB4531967765_1920x1080.jpg&rf=LaDigue_1920x1080.jpg&pid=hp",
            "urlbase": "/th?id=OHR.CanaryWharfStation_EN-GB4531967765",
            "copyright": "Canary Wharf underground station, London (© AWL Images/DanitaDelimont.com)",
            "copyrightlink": "https://www.bing.com/search?q=Canary+Wharf+underground+station+&form=hpcapt&filters=HpDate%3a%2220231017_2300%22",
            "title": "The holy train-ity",
            "quiz": "/search?q=Bing+homepage+quiz&filters=WQOskey:%22HPQuiz_20231017_CanaryWharfStation%22&FORM=HPQUIZ",
            "wp": true,
            "hsh": "55c405c64d53218b2947d11ed6dd375f",
            "drk": 1,
            "top": 1,
            "bot": 1,
            "hs": []
        },
        {
            "startdate": "20231016",
            "fullstartdate": "202310162300",
            "enddate": "20231017",
            "url": "/th?id=OHR.SpreadsheetDay_EN-GB0904502702_1920x1080.jpg&rf=LaDigue_1920x1080.jpg&pid=hp",
            "urlbase": "/th?id=OHR.SpreadsheetDay_EN-GB0904502702",
            "copyright": "Ancient carved texts from Persepolis, Iran (© George Hall/Alamy)",
            "copyrightlink": "https://www.bing.com/search?q=cuneiform&form=hpcapt&filters=HpDate%3a%2220231016_2300%22",
            "title": "Distant-past data",
            "quiz": "/search?q=Bing+homepage+quiz&filters=WQOskey:%22HPQuiz_20231016_SpreadsheetDay%22&FORM=HPQUIZ",
            "wp": false,
            "hsh": "a9db3d78b9e9c9266f68b4805e2c0b03",
            "drk": 1,
            "top": 1,
            "bot": 1,
            "hs": []
        },
        {
            "startdate": "20231015",
            "fullstartdate": "202310152300",
            "enddate": "20231016",
            "url": "/th?id=OHR.GoldenEnchantments_EN-GB4003650281_1920x1080.jpg&rf=LaDigue_1920x1080.jpg&pid=hp",
            "urlbase": "/th?id=OHR.GoldenEnchantments_EN-GB4003650281",
            "copyright": "Golden larches and Prusik Peak, Enchantments, Washington, USA (© Jim Patterson/Tandem Stills + Motion)",
            "copyrightlink": "https://www.bing.com/search?q=the+enchantments+washington&form=hpcapt&filters=HpDate%3a%2220231015_2300%22",
            "title": "Enchanting indeed",
            "quiz": "/search?q=Bing+homepage+quiz&filters=WQOskey:%22HPQuiz_20231015_GoldenEnchantments%22&FORM=HPQUIZ",
            "wp": true,
            "hsh": "daea86d660bb100f3a643c832e352ea2",
            "drk": 1,
            "top": 1,
            "bot": 1,
            "hs": []
        },
        {
            "startdate": "20231014",
            "fullstartdate": "202310142300",
            "enddate": "20231015",
            "url": "/th?id=OHR.AutumnHedgehog_EN-GB3716298220_1920x1080.jpg&rf=LaDigue_1920x1080.jpg&pid=hp",
            "urlbase": "/th?id=OHR.AutumnHedgehog_EN-GB3716298220",
            "copyright": "European hedgehog sheltering in tree bark, Sussex (© Jules Cox/Minden Pictures)",
            "copyrightlink": "https://www.bing.com/search?q=European+hedgehog&form=hpcapt&filters=HpDate%3a%2220231014_2300%22",
            "title": "This spot's taken",
            "quiz": "/search?q=Bing+homepage+quiz&filters=WQOskey:%22HPQuiz_20231014_AutumnHedgehog%22&FORM=HPQUIZ",
            "wp": true,
            "hsh": "765824e52ce88a678c9a4e50b26aafed",
            "drk": 1,
            "top": 1,
            "bot": 1,
            "hs": []
        },
        {
            "startdate": "20231013",
            "fullstartdate": "202310132300",
            "enddate": "20231014",
            "url": "/th?id=OHR.RingEclipse_EN-GB2487189935_1920x1080.jpg&rf=LaDigue_1920x1080.jpg&pid=hp",
            "urlbase": "/th?id=OHR.RingEclipse_EN-GB2487189935",
            "copyright": "'Ring of fire' annular solar eclipse, Doha, Qatar (© Sorin Furcoi/Getty Images)",
            "copyrightlink": "https://www.bing.com/search?q=Annular+solar+eclipse&form=hpcapt&filters=HpDate%3a%2220231013_2300%22",
            "title": "And it burns, burns, burns",
            "quiz": "/search?q=Bing+homepage+quiz&filters=WQOskey:%22HPQuiz_20231013_RingEclipse%22&FORM=HPQUIZ",
            "wp": true,
            "hsh": "16875c5880227dfcd0c22332fac52398",
            "drk": 1,
            "top": 1,
            "bot": 1,
            "hs": []
        }
    ],
    "tooltips": {
        "loading": "Loading...",
        "previous": "Previous image",
        "next": "Next image",
        "walle": "This image is not available to download as wallpaper.",
        "walls": "Download this image. Use of this image is restricted to wallpaper only."
    }
}