{
    "images": [
        {
            "startdate": "20240718",
            "fullstartdate": "202407182300",
            "enddate": "20240719",
            "url": "/th?id=OHR.YoungJaguar_EN-GB7435202533_1920x1080.jpg&rf=LaDigue_1920x1080.jpg&pid=hp",
            "urlbase": "/th?id=OHR.YoungJaguar_EN-GB7435202533",
            "copyright": "A young jaguar on a riverbank, Pantanal, Brazil (© Tambako the Jaguar/Getty Images)",
            "copyrightlink": "https://www.bing.com/search?q=Jaguar+animal&form=hpcapt&filters=HpDate%3a%2220240718_2300%22",
            "title": "Clever camouflage",
            "quiz": "/search?q=Bing+homepage+quiz&filters=WQOskey:%22HPQuiz_20240718_YoungJaguar%22&FORM=HPQUIZ",
            "wp": true,
            "hsh": "0d31d5b2d44f16e39c9390fa468bdc87",
            "drk": 1,
            "top": 1,
            "bot": 1,
            "hs": []
        },
        {
            "startdate": "20240717",
            "fullstartdate": "202407172300",
            "enddate": "20240718",
            "url": "/th?id=OHR.MayotteCoral_EN-GB7192983287_1920x1080.jpg&rf=LaDigue_1920x1080.jpg&pid=hp",
            "urlbase": "/th?id=OHR.MayotteCoral_EN-GB7192983287",
            "copyright": "Coral reef in the Indian Ocean, Mayotte, France (© Gabriel Barathieu/Minden Pictures)",
            "copyrightlink": "https://www.bing.com/search?q=Coral+Reef+Awareness+Week&form=hpcapt&filters=HpDate%3a%2220240717_2300%22",
            "title": "Deep and meaningful",
            "quiz": "/search?q=Bing+homepage+quiz&filters=WQOskey:%22HPQuiz_20240717_MayotteCoral%22&FORM=HPQUIZ",
            "wp": true,
            "hsh": "c9bfccc03398c266bdd1b985eb5acca7",
            "drk": 1,
            "top": 1,
            "bot": 1,
            "hs": []
        },
        {
            "startdate": "20240716",
            "fullstartdate": "202407162300",
            "enddate": "20240717",
            "url": "/th?id=OHR.MedievalRothenburg_EN-GB0016545589_1920x1080.jpg&rf=LaDigue_1920x1080.jpg&pid=hp",
            "urlbase": "/th?id=OHR.MedievalRothenburg_EN-GB0016545589",
            "copyright": "Medieval city of Rothenburg ob der Tauber, Germany (© kanuman/Getty Images)",
            "copyrightlink": "https://www.bing.com/search?q=Rothenburg+ob+der+Tauber+Germany&form=hpcapt&filters=HpDate%3a%2220240716_2300%22",
            "title": "Towering with history",
            "quiz": "/search?q=Bing+homepage+quiz&filters=WQOskey:%22HPQuiz_20240716_MedievalRothenburg%22&FORM=HPQUIZ",
            "wp": true,
            "hsh": "4ccf998468111fb20632a7e5fd02b2b8",
            "drk": 1,
            "top": 1,
            "bot": 1,
            "hs": []
        },
        {
            "startdate": "20240715",
            "fullstartdate": "202407152300",
            "enddate": "20240716",
            "url": "/th?id=OHR.AncientOrkney_EN-GB6273973665_1920x1080.jpg&rf=LaDigue_1920x1080.jpg&pid=hp",
            "urlbase": "/th?id=OHR.AncientOrkney_EN-GB6273973665",
            "copyright": "The neolithic settlement of Skara Brae, Orkney, Scotland (© Paul Williams - FunkyStock/Getty Images)",
            "copyrightlink": "https://www.bing.com/search?q=Festival+of+British+Archaeology&form=hpcapt&filters=HpDate%3a%2220240715_2300%22",
            "title": "Digging into the past",
            "quiz": "/search?q=Bing+homepage+quiz&filters=WQOskey:%22HPQuiz_20240715_AncientOrkney%22&FORM=HPQUIZ",
            "wp": true,
            "hsh": "587e32a12013951c922c16c0853e8bcb",
            "drk": 1,
            "top": 1,
            "bot": 1,
            "hs": []
        },
        {
            "startdate": "20240714",
            "fullstartdate": "202407142300",
            "enddate": "20240715",
            "url": "/th?id=OHR.TateishiPark_EN-GB5935394849_1920x1080.jpg&rf=LaDigue_1920x1080.jpg&pid=hp",
            "urlbase": "/th?id=OHR.TateishiPark_EN-GB5935394849",
            "copyright": "Tateishi Park, Kanagawa Prefecture, Japan (© blew_s/Shutterstock)",
            "copyrightlink": "https://www.bing.com/search?q=Marine+Day+Japan&form=hpcapt&filters=HpDate%3a%2220240714_2300%22",
            "title": "Seas the day",
            "quiz": "/search?q=Bing+homepage+quiz&filters=WQOskey:%22HPQuiz_20240714_TateishiPark%22&FORM=HPQUIZ",
            "wp": true,
            "hsh": "f58eb6dc321fecd066d380659bdfeb93",
            "drk": 1,
            "top": 1,
            "bot": 1,
            "hs": []
        },
        {
            "startdate": "20240713",
            "fullstartdate": "202407132300",
            "enddate": "20240714",
            "url": "/th?id=OHR.OwlSiblings_EN-GB5626247823_1920x1080.jpg&rf=LaDigue_1920x1080.jpg&pid=hp",
            "urlbase": "/th?id=OHR.OwlSiblings_EN-GB5626247823",
            "copyright": "Burrowing owl chicks near a burrow, Wyoming, USA (© Danita Delimont/Getty Images)",
            "copyrightlink": "https://www.bing.com/search?q=Burrowing+owl&form=hpcapt&filters=HpDate%3a%2220240713_2300%22",
            "title": "Owl be there for you!",
            "quiz": "/search?q=Bing+homepage+quiz&filters=WQOskey:%22HPQuiz_20240713_OwlSiblings%22&FORM=HPQUIZ",
            "wp": true,
            "hsh": "bab337c6126785c53fda2a5d19f42c35",
            "drk": 1,
            "top": 1,
            "bot": 1,
            "hs": []
        },
        {
            "startdate": "20240712",
            "fullstartdate": "202407122300",
            "enddate": "20240713",
            "url": "/th?id=OHR.CappadociaRocks_EN-GB3775326662_1920x1080.jpg&rf=LaDigue_1920x1080.jpg&pid=hp",
            "urlbase": "/th?id=OHR.CappadociaRocks_EN-GB3775326662",
            "copyright": "Fairy chimneys and cave dwellings in Cappadocia, Türkiye (© Storm Is Me/Shutterstock)",
            "copyrightlink": "https://www.bing.com/search?q=Rocks&form=hpcapt&filters=HpDate%3a%2220240712_2300%22",
            "title": "Sedimentary, my dear",
            "quiz": "/search?q=Bing+homepage+quiz&filters=WQOskey:%22HPQuiz_20240712_CappadociaRocks%22&FORM=HPQUIZ",
            "wp": true,
            "hsh": "8e3f386365a932a66fc3992fb0772bbf",
            "drk": 1,
            "top": 1,
            "bot": 1,
            "hs": []
        },
        {
            "startdate": "20240711",
            "fullstartdate": "202407112300",
            "enddate": "20240712",
            "url": "/th?id=OHR.RainierWildflowers_EN-GB3567513605_1920x1080.jpg&rf=LaDigue_1920x1080.jpg&pid=hp",
            "urlbase": "/th?id=OHR.RainierWildflowers_EN-GB3567513605",
            "copyright": "Wildflowers in Mount Rainier National Park, Washington, USA (© RomanKhomlyak/Getty Images)",
            "copyrightlink": "https://www.bing.com/search?q=Mount+Rainier+National+Park&form=hpcapt&filters=HpDate%3a%2220240711_2300%22",
            "title": "Come Rainier or shine",
            "quiz": "/search?q=Bing+homepage+quiz&filters=WQOskey:%22HPQuiz_20240711_RainierWildflowers%22&FORM=HPQUIZ",
            "wp": true,
            "hsh": "dc0c700ff47019b5c2a0023e3f860b32",
            "drk": 1,
            "top": 1,
            "bot": 1,
            "hs": []
        }
    ],
    "tooltips": {
        "loading": "Loading...",
        "previous": "Previous image",
        "next": "Next image",
        "walle": "This image is not available to download as wallpaper.",
        "walls": "Download this image. Use of this image is restricted to wallpaper only."
    }
}